davidkhala/data/base/common.py
davidkhala/data/base/sql.py
davidkhala/data/base/couchbase/README.md
davidkhala/data/base/couchbase/__init__.py
davidkhala/data/base/couchbase/capella/__init__.py
davidkhala/data/base/couchbase/capella/bucket.py
davidkhala/data/base/couchbase/capella/cluster.py
davidkhala/data/base/couchbase/capella/http.py
davidkhala/data/base/couchbase/capella/organization.py
davidkhala/data/base/couchbase/capella/project.py
davidkhala/data/base/milvus/__init__.py
davidkhala/data/base/mysql/__init__.py
davidkhala_databases-0.1.1.dist-info/METADATA
davidkhala_databases-0.1.1.dist-info/WHEEL
davidkhala_databases-0.1.1.dist-info/RECORD
