Metadata-Version: 2.4
Name: davidkhala.databases
Version: 0.1.1
Author-email: David Liu <david-khala@hotmail.com>
Requires-Python: >=3.11
Provides-Extra: couchbase
Requires-Dist: couchbase; extra == 'couchbase'
Requires-Dist: davidkhala-utils[http-request]; extra == 'couchbase'
Provides-Extra: duck
Requires-Dist: duckdb; extra == 'duck'
Provides-Extra: milvus
Requires-Dist: hf-xet; extra == 'milvus'
Requires-Dist: pymilvus[milvus-lite,model]; extra == 'milvus'
Provides-Extra: mysql
Requires-Dist: sqlalchemy; extra == 'mysql'
